setup.py
distributions_ng/Binomialdistribution.py
distributions_ng/Gaussiandistribution.py
distributions_ng/Generaldistribution.py
distributions_ng/__init__.py
distributions_ng.egg-info/PKG-INFO
distributions_ng.egg-info/SOURCES.txt
distributions_ng.egg-info/dependency_links.txt
distributions_ng.egg-info/not-zip-safe
distributions_ng.egg-info/top_level.txt