Metadata-Version: 1.0
Name: distributions-ng
Version: 1.0
Summary: Gaussian distributions
Home-page: UNKNOWN
Author: Nitin Raj
Author-email: nitingupta180@gmail.com
License: UNKNOWN
Platform: UNKNOWN
